ranobelib_loader/__init__.py
ranobelib_loader/rules.py
ranobelib_loader/schema.py
ranobelib_loader-0.1.1.dist-info/licenses/LICENCE.md
ranobelib_loader-0.1.1.dist-info/METADATA
ranobelib_loader-0.1.1.dist-info/WHEEL
ranobelib_loader-0.1.1.dist-info/top_level.txt
ranobelib_loader-0.1.1.dist-info/RECORD
