Metadata-Version: 2.4
Name: ranobelib-loader
Version: 0.1.1
Summary: Неофициальное API для загрузки контента на сайт ranobelib.
Author-email: Armontex <windle1337@gmail.com>
Classifier: License :: OSI Approved :: BSD License
Requires-Python: >=3.10
License-File: LICENCE.md
Requires-Dist: lxml==5.4.0
Requires-Dist: Markdown==3.8.2
Requires-Dist: prosemirror==0.5.2
Requires-Dist: Requests==2.32.4
Dynamic: license-file
